[
{
"issue_id": "ISSUE-001",
"title": "Fan speed does not follow expected thermal table under GPU stress",
"milestone": "Pilot",
"severity": "Sev1",
"is_gating": true,
"reported_by": "Validation",
"suspected_owner": "BIOS",
"impacted_teams": ["BIOS", "Thermal", "Validation"],
"reproducible": true,
"machine_available": true,
"current_status": "Open",
"customer_impact": "Potential thermal policy failure under high GPU workload",
"schedule_impact": "Blocks Pilot exit",
"recommended_action": "Confirm latest Thermal fan table delivery and BIOS integration status"
},
{
"issue_id": "ISSUE-002",
"title": "Redfish sensor inventory missing GPU temperature field",
"milestone": "Feature Complete",
"severity": "Sev2",
"is_gating": false,
"reported_by": "Validation",
"suspected_owner": "BMC",
"impacted_teams": ["BMC", "GPU", "Validation", "Customer Support"],
"reproducible": true,
"machine_available": true,
"current_status": "Open",
"customer_impact": "Remote management telemetry incomplete",
"schedule_impact": "May impact customer qualification",
"recommended_action": "Check BMC telemetry mapping and GPU sensor source"
},
{
"issue_id": "ISSUE-003",
"title": "OS image missing storage controller driver package",
"milestone": "Pilot",
"severity": "Sev1",
"is_gating": true,
"reported_by": "Validation",
"suspected_owner": "Driver / OS",
"impacted_teams": ["Driver", "OS", "System Image", "Validation"],
"reproducible": true,
"machine_available": true,
"current_status": "Open",
"customer_impact": "System cannot complete storage validation",
"schedule_impact": "Blocks Pilot validation",
"recommended_action": "Update driver package and regenerate OS image"
},
{
"issue_id": "ISSUE-004",
"title": "PCIe device enumeration unstable after warm reboot",
"milestone": "Pilot",
"severity": "Sev1",
"is_gating": true,
"reported_by": "Validation",
"suspected_owner": "BIOS",
"impacted_teams": ["BIOS", "EE", "Driver", "Validation"],
"reproducible": false,
"machine_available": false,
"current_status": "Needs Reproduction",
"customer_impact": "Potential device availability issue after reboot",
"schedule_impact": "High risk if reproducible",
"recommended_action": "Secure failing system for BIOS and EE debug"
},
{
"issue_id": "ISSUE-005",
"title": "Factory diagnostic tool cannot read BMC firmware version",
"milestone": "Production Readiness",
"severity": "Sev2",
"is_gating": false,
"reported_by": "Factory",
"suspected_owner": "Factory / Diagnostics",
"impacted_teams": ["Factory", "Diagnostics", "BMC", "Manufacturing"],
"reproducible": true,
"machine_available": true,
"current_status": "Open",
"customer_impact": "No direct customer impact, but factory readiness is incomplete",
"schedule_impact": "May delay production build exit",
"recommended_action": "Align BMC version query interface with diagnostic tool owner"
},
{
"issue_id": "ISSUE-006",
"title": "Secure Boot default setting does not match customer requirement",
"milestone": "Production Readiness",
"severity": "Sev2",
"is_gating": false,
"reported_by": "Quality",
"suspected_owner": "BIOS",
"impacted_teams": ["BIOS", "Security", "OS", "Quality"],
"reproducible": true,
"machine_available": true,
"current_status": "Open",
"customer_impact": "Customer security configuration mismatch",
"schedule_impact": "Requires decision before release",
"recommended_action": "Confirm customer default policy and update BIOS setup default if required"
},
{
"issue_id": "ISSUE-007",
"title": "Long-run stress test fails after 72 hours with intermittent system hang",
"milestone": "Pilot",
"severity": "Sev1",
"is_gating": true,
"reported_by": "Validation",
"suspected_owner": "Unknown",
"impacted_teams": ["BIOS", "BMC", "Driver", "OS", "Validation"],
"reproducible": true,
"machine_available": true,
"current_status": "Open",
"customer_impact": "System stability risk under sustained workload",
"schedule_impact": "Blocks Production Readiness if unresolved",
"recommended_action": "Collect BIOS, BMC, OS, driver, and stress logs for cross-layer triage"
}
]
